bctools/__init__.py
bctools/plots.py
bctools/thresholds.py
bctools/utilities.py
binclass_tools-1.1.2.dist-info/METADATA
binclass_tools-1.1.2.dist-info/WHEEL
binclass_tools-1.1.2.dist-info/top_level.txt
binclass_tools-1.1.2.dist-info/RECORD
