Metadata-Version: 2.1
Name: binclass-tools
Version: 1.1.2
Summary: A set of tools that facilitates the analysis of binary classification problems
Home-page: https://github.com/lucazav/binclass-tools/
Author: Luca Zavarella, Greta Villa
Author-email: lucazavarella@outlook.com
Project-URL: Source, https://github.com/lucazav/binclass-tools/
Keywords: binary,classification,confusion,matrix,threshold,plot,precision,recall
Classifier: Development Status :: 3 - Alpha
Classifier: Intended Audience :: Other Audience
Classifier: License :: OSI Approved :: BSD License
Classifier: Programming Language :: Python :: 3
Classifier: Programming Language :: Python :: 3.6
Classifier: Programming Language :: Python :: 3.7
Classifier: Programming Language :: Python :: 3.8
Classifier: Programming Language :: Python :: 3.9
Classifier: Programming Language :: Python :: 3.10
Classifier: Programming Language :: Python :: 3.11
Requires-Python: >=3.6
Requires-Dist: numpy
Requires-Dist: pandas
Requires-Dist: scikit-learn (>=0.22.1)
Requires-Dist: matplotlib
Requires-Dist: plotly (>=5.5.0)
Requires-Dist: nbformat (>=4.2.0)
